automabot/__init__.py
automabot/__main__.py
automabot/automation.py
automabot/bot.py
automabot/default_config.toml
automabot/tools.py
automabot/web.py
automabot-0.3.2.dist-info/DESCRIPTION.rst
automabot-0.3.2.dist-info/METADATA
automabot-0.3.2.dist-info/RECORD
automabot-0.3.2.dist-info/WHEEL
automabot-0.3.2.dist-info/entry_points.txt
automabot-0.3.2.dist-info/metadata.json
automabot-0.3.2.dist-info/pbr.json
automabot-0.3.2.dist-info/top_level.txt
