Metadata-Version: 2.0
Name: automabot
Version: 0.3.2
Summary: Automabot bot for Discord.
Home-page: https://github.com/73VW/AutomaBot
Author: 73VW
Author-email: mael.pedretti@he-arc.ch
License: MIT
Platform: UNKNOWN
Classifier: Development Status :: 3 - Alpha
Classifier: Environment :: Console
Classifier: Intended Audience :: Education
Classifier: Operating System :: MacOS :: MacOS X
Classifier: Operating System :: Microsoft :: Windows
Classifier: Operating System :: POSIX
Classifier: Programming Language :: Python :: 3 :: Only
Classifier: Programming Language :: Python :: 3.6
Classifier: Programming Language :: Python :: Implementation :: CPython
Classifier: Topic :: Home Automation
Requires-Dist: discord.py (>=0.16.8)
Requires-Dist: pyfiglet (>=0.7.5)
Requires-Dist: toml (>=0.9.2)
Provides-Extra: docs
Requires-Dist: Sphinx (>=1.6.0); extra == 'docs'
Requires-Dist: sphinxcontrib-trio; extra == 'docs'
Provides-Extra: fast
Requires-Dist: aiodns; extra == 'fast'
Requires-Dist: cchardet; extra == 'fast'
Provides-Extra: qa
Requires-Dist: flake8; extra == 'qa'
Requires-Dist: isort; extra == 'qa'
Requires-Dist: pycodestyle; extra == 'qa'
Requires-Dist: pydocstyle; extra == 'qa'
